stanley/__init__.py
stanley/agent.py
stanley/base_tool.py
stanley/errors.py
stanley/history.py
stanley/models.py
stanley/prompts/system-prompt.txt
stanley/tools/__init__.py
stanley/tools/send_message.py
stanley_ai-0.0.1.dist-info/METADATA
stanley_ai-0.0.1.dist-info/WHEEL
stanley_ai-0.0.1.dist-info/licenses/LICENSE
stanley_ai-0.0.1.dist-info/RECORD
